LICENSE.txt
README.md
setup.py
bq_loader/__init__.py
bq_loader/__main__.py
bq_loader/utils.py
bq_loader.egg-info/PKG-INFO
bq_loader.egg-info/SOURCES.txt
bq_loader.egg-info/dependency_links.txt
bq_loader.egg-info/entry_points.txt
bq_loader.egg-info/not-zip-safe
bq_loader.egg-info/requires.txt
bq_loader.egg-info/top_level.txt