Metadata-Version: 2.1
Name: bq-loader
Version: 0.1.5
Summary: Interactive Command Line Interface for Google BigQuery
Home-page: https://github.com/naustica/bq_loader
Author: Nick Haupka
Author-email: nick.haupka@gmail.com
License: MIT
Project-URL: Source, https://github.com/naustica/bq_loader
Project-URL: Tracker, https://github.com/naustica/bq_loader/issues
Keywords: BigQuery,Google,Bucket,Cloud,Storage,Data Analytic
Platform: UNKNOWN
Classifier: Development Status :: 3 - Alpha
Classifier: License :: OSI Approved :: MIT License
Classifier: Operating System :: OS Independent
Classifier: Programming Language :: Python :: 3.9
Provides-Extra: dev
License-File: LICENSE.txt
